nbodyx/__init__.py
nbodyx/constants.py
nbodyx/ode.py
nbodyx/rendering/__init__.py
nbodyx/rendering/opencv.py
nbodyx-0.0.1rc56.post1.dist-info/WHEEL
nbodyx-0.0.1rc56.post1.dist-info/METADATA
nbodyx-0.0.1rc56.post1.dist-info/RECORD
